finitude/__init__.py
finitude/__main__.py
finitude/finitude.py
finitude/frames.py
finitude/registers.py
finitude/sniffserver.py
finitude-0.1.1.dist-info/LICENSE
finitude-0.1.1.dist-info/METADATA
finitude-0.1.1.dist-info/WHEEL
finitude-0.1.1.dist-info/top_level.txt
finitude-0.1.1.dist-info/RECORD
