Metadata-Version: 2.1
Name: finitude
Version: 0.1.1
Summary: Controls and shows status of Carrier Infinity and Bryant Evolution HVAC systems.
Home-page: https://github.com/dulitz/finitude
Author: Daniel Dulitz
Author-email: dulitz@gmail.com
License: UNKNOWN
Project-URL: Wiki, https://github.com/dulitz/finitude/wiki
Project-URL: Bug Tracker, https://github.com/dulitz/finitude/issues
Platform: UNKNOWN
Classifier: Programming Language :: Python :: 3
Classifier: License :: OSI Approved :: MIT License
Classifier: Operating System :: OS Independent
Requires-Python: >=3.7
License-File: LICENSE
Requires-Dist: pyserial
Requires-Dist: prometheus-client
Requires-Dist: PyYAML
